confect/__init__.py
confect/conf.py
confect/conf_depot.py
confect/error.py
confect/prop_type.py
confect-0.4.3.dist-info/WHEEL
confect-0.4.3.dist-info/METADATA
confect-0.4.3.dist-info/RECORD
