Metadata-Version: 2.1
Name: confect
Version: 0.4.3
Summary: a Python configuration library loads Python configuration files
Home-page: https://github.com/d2207197/confect
License: Apache-2.0
Keywords: setting,configuration,config
Author: Yen, Tzu-Hsi
Author-email: joseph.yen@gmail.com
Requires-Python: >=3.6
Classifier: License :: OSI Approved :: Apache Software License
Classifier: Programming Language :: Python :: 3
Classifier: Programming Language :: Python :: 3.6
Classifier: Programming Language :: Python :: 3.7
Classifier: Programming Language :: Python :: 3.8
Classifier: Topic :: Software Development :: Libraries :: Python Modules
Provides-Extra: click
Provides-Extra: pendulum
Requires-Dist: click (>=2.0); extra == "click"
Requires-Dist: pendulum (>=2.0.0,<3.0.0); extra == "pendulum"
Project-URL: Documentation, https://github.com/d2207197/confect
Project-URL: Repository, https://github.com/d2207197/confect
